README.rst
setup.py
django_autoshard/__init__.py
django_autoshard/apps.py
django_autoshard/factory.py
django_autoshard/managers.py
django_autoshard/models.py
django_autoshard/querysets.py
django_autoshard/routers.py
django_autoshard/settings.py
django_autoshard/shard.py
django_autoshard/utils.py
django_autoshard.egg-info/PKG-INFO
django_autoshard.egg-info/SOURCES.txt
django_autoshard.egg-info/dependency_links.txt
django_autoshard.egg-info/requires.txt
django_autoshard.egg-info/top_level.txt
django_autoshard/management/__init__.py
django_autoshard/management/commands/__init__.py
django_autoshard/management/commands/create_shards.py
django_autoshard/management/commands/drop_constraints.py
django_autoshard/management/commands/drop_shards.py
django_autoshard/management/commands/list_shards.py
django_autoshard/management/commands/migrate_shards.py
django_autoshard/tests/__init__.py
django_autoshard/tests/base.py
django_autoshard/tests/runner.py
django_autoshard/tests/settings.py
django_autoshard/tests/test_user.py
django_autoshard/tests/fakeapp/__init__.py
django_autoshard/tests/fakeapp/apps.py
django_autoshard/tests/fakeapp/models.py
django_autoshard/tests/fakeapp/migrations/0001_initial.py
django_autoshard/tests/fakeapp/migrations/__init__.py