Metadata-Version: 1.1
Name: django-autoshard
Version: 1.2.0
Summary: A Django library that makes sharding easy.
Home-page: https://github.com/cipriantarta/django-autoshard
Author: Ciprian Tarta
Author-email: me@cipriantarta.ro
License: BSD
Keywords: django shard sharding
Platform: UNKNOWN
Classifier: Environment :: Web Environment
Classifier: Framework :: Django
Classifier: Intended Audience :: Developers
Classifier: License :: OSI Approved :: BSD License
Classifier: Operating System :: OS Independent
Classifier: Programming Language :: Python :: 2.7
Classifier: Programming Language :: Python :: 3.4
Classifier: Programming Language :: Python :: 3.5
Classifier: Topic :: Software Development :: Libraries :: Python Modules
Classifier: Framework :: Django
Classifier: Framework :: Django :: 1.7
Classifier: Framework :: Django :: 1.8
Classifier: Framework :: Django :: 1.9
